amb_core/__init__.py
amb_core/broker.py
amb_core/bus.py
amb_core/dlq.py
amb_core/hf_utils.py
amb_core/memory_broker.py
amb_core/models.py
amb_core/persistence.py
amb_core/schema.py
amb_core/tracing.py
amb_core/adapters/__init__.py
amb_core/adapters/kafka_broker.py
amb_core/adapters/rabbitmq_broker.py
amb_core/adapters/redis_broker.py
amb_core-0.3.0.dist-info/licenses/LICENSE
amb_core-0.3.0.dist-info/METADATA
amb_core-0.3.0.dist-info/WHEEL
amb_core-0.3.0.dist-info/top_level.txt
amb_core-0.3.0.dist-info/RECORD
