Metadata-Version: 2.4
Name: amb-core
Version: 0.3.0
Summary: A lightweight, broker-agnostic message bus designed specifically for AI Agents
Author: Imran Siddique
Project-URL: Homepage, https://github.com/imran-siddique/amb
Project-URL: Repository, https://github.com/imran-siddique/amb
Project-URL: Documentation, https://github.com/imran-siddique/amb#readme
Project-URL: Bug Tracker, https://github.com/imran-siddique/amb/issues
Project-URL: Changelog, https://github.com/imran-siddique/amb/releases
Classifier: Development Status :: 3 - Alpha
Classifier: Intended Audience :: Developers
Classifier: License :: OSI Approved :: MIT License
Classifier: Programming Language :: Python :: 3
Classifier: Programming Language :: Python :: 3.8
Classifier: Programming Language :: Python :: 3.9
Classifier: Programming Language :: Python :: 3.10
Classifier: Programming Language :: Python :: 3.11
Classifier: Programming Language :: Python :: 3.12
Requires-Python: >=3.8
License-File: LICENSE
Requires-Dist: pydantic>=2.0.0
Requires-Dist: anyio>=3.0.0
Requires-Dist: aiofiles>=23.0.0
Provides-Extra: redis
Requires-Dist: redis>=4.0.0; extra == "redis"
Provides-Extra: rabbitmq
Requires-Dist: aio-pika>=9.0.0; extra == "rabbitmq"
Provides-Extra: kafka
Requires-Dist: aiokafka>=0.8.0; extra == "kafka"
Provides-Extra: all
Requires-Dist: redis>=4.0.0; extra == "all"
Requires-Dist: aio-pika>=9.0.0; extra == "all"
Requires-Dist: aiokafka>=0.8.0; extra == "all"
Provides-Extra: dev
Requires-Dist: pytest>=7.0.0; extra == "dev"
Requires-Dist: pytest-asyncio>=0.21.0; extra == "dev"
Requires-Dist: pytest-cov>=4.0.0; extra == "dev"
Provides-Extra: keywords
Requires-Dist: message-bus; extra == "keywords"
Requires-Dist: ai-agents; extra == "keywords"
Requires-Dist: pubsub; extra == "keywords"
Requires-Dist: async; extra == "keywords"
Requires-Dist: broker-agnostic; extra == "keywords"
Requires-Dist: redis; extra == "keywords"
Requires-Dist: rabbitmq; extra == "keywords"
Requires-Dist: kafka; extra == "keywords"
Requires-Dist: multi-agent; extra == "keywords"
Requires-Dist: llm; extra == "keywords"
Dynamic: license-file
